Metadata-Version: 2.1
Name: calculadorasalario
Version: 0.0.1
Summary: Função para cálculo de pagamento
Home-page: https://github.com/isabela-rossetti/pacote_python
Author: Isabela Rossetti
Author-email: isabelarossetti.ir@gmail.com
License: MIT License
Keywords: Calculadora
License-File: LICENSE.txt
